hardcopy/__init__.py
hardcopy/downloader.py
hardcopy-0.1.0.data/scripts/hardcopy
hardcopy-0.1.0.dist-info/DESCRIPTION.rst
hardcopy-0.1.0.dist-info/METADATA
hardcopy-0.1.0.dist-info/RECORD
hardcopy-0.1.0.dist-info/WHEEL
hardcopy-0.1.0.dist-info/metadata.json
hardcopy-0.1.0.dist-info/top_level.txt
