Metadata-Version: 2.0
Name: hardcopy
Version: 0.1.0
Summary: Tool to download and export Google Drive files
Home-page: http://github.com/joshpaulchan/hardcopy-python
Author: Joshua Paul A. Chan (@joshpaulchan)
Author-email: joshpaulchan@gmail.com
License: UNKNOWN
Platform: UNKNOWN
Requires-Dist: appdirs (==1.4.3)
Requires-Dist: click (==6.7)
Requires-Dist: google-api-python-client (==1.6.2)
Requires-Dist: httplib2 (==0.10.3)
Requires-Dist: oauth2client (==4.1.0)
Requires-Dist: packaging (==16.8)
Requires-Dist: pyasn1 (==0.2.3)
Requires-Dist: pyasn1-modules (==0.0.8)
Requires-Dist: pyparsing (==2.2.0)
Requires-Dist: rsa (==3.4.2)
Requires-Dist: six (==1.10.0)
Requires-Dist: uritemplate (==3.0.0)
